pipdot/__init__.py
pipdot/__main__.py
pipdot/boolean_optional_action.py
pipdot/version.py
pipdot/templates/default.dot.j2
pipdot-0.2.dist-info/LICENSE
pipdot-0.2.dist-info/METADATA
pipdot-0.2.dist-info/WHEEL
pipdot-0.2.dist-info/entry_points.txt
pipdot-0.2.dist-info/top_level.txt
pipdot-0.2.dist-info/RECORD
