Metadata-Version: 2.1
Name: pipdot
Version: 0.2
Summary: Generate a graphviz dot file representing installed PyPI distributions.
Home-page: https://github.com/tanbro/pipdot
Author: liu xue yan
Author-email: liu_xue_yan@foxmail.com
License: BSD 3-Clause License
Keywords: pypi,pip,distribution,dist,graph,graphviz,dot,package,dependency,dependency-graph
Platform: UNKNOWN
Classifier: Development Status :: 5 - Production/Stable
Classifier: Programming Language :: Python :: 3
Classifier: License :: OSI Approved :: BSD License
Classifier: Topic :: Software Development
Classifier: Intended Audience :: Developers
Requires-Python: !=3.0.*,!=3.1.*,!=3.2.*,!=3.3.*,!=3.4.*,>=2.7
License-File: LICENSE
Requires-Dist: pip (>=22.0)
Requires-Dist: Jinja2 (<4.0,>=2.0)
